Solver/PenCF.py
Solver/SLPG.py
Solver/__init__.py
manifold/Stiefel.py
manifold/__init__.py
pystmopt-0.1.0.data/data/LICENSE
pystmopt-0.1.0.data/data/README.md
pystmopt-0.1.0.dist-info/METADATA
pystmopt-0.1.0.dist-info/RECORD
pystmopt-0.1.0.dist-info/WHEEL
pystmopt-0.1.0.dist-info/top_level.txt
utility/__init__.py
utility/utility.py
